docs/Makefile
docs/authors.rst
docs/changelog.rst
docs/conf.py
docs/contributing.rst
docs/index.rst
docs/license.rst
docs/readme.rst
docs/requirements.txt
docs/_static/.gitignore
patricesorter/__init__.py
patricesorter/__main__.py
patricesorter/_version.py
patricesorter/lib/__init__.py
patricesorter/lib/defaults.py
patricesorter/lib/get_opts.py
patricesorter/lib/pricing.py
patricesorter-1.0.0.dist-info/LICENSE.txt
patricesorter-1.0.0.dist-info/METADATA
patricesorter-1.0.0.dist-info/WHEEL
patricesorter-1.0.0.dist-info/entry_points.txt
patricesorter-1.0.0.dist-info/top_level.txt
patricesorter-1.0.0.dist-info/RECORD
